MANIFEST.in
README.rst
requirements.txt
setup.py
contactbox/__init__.py
contactbox/admin.py
contactbox/forms.py
contactbox/models.py
contactbox/test_runner.py
contactbox/views.py
contactbox.egg-info/PKG-INFO
contactbox.egg-info/SOURCES.txt
contactbox.egg-info/dependency_links.txt
contactbox.egg-info/not-zip-safe
contactbox.egg-info/top_level.txt
contactbox/management/__init__.py
contactbox/management/commands/__init__.py
contactbox/management/commands/remind_contact.py
contactbox/migrations/0001_initial.py
contactbox/migrations/__init__.py
contactbox/templates/contactbox/email.txt
contactbox/test_project/__init__.py
contactbox/test_project/settings.py
contactbox/test_project/urls.py
contactbox/tests/__init__.py
contactbox/tests/test_main.py