Metadata-Version: 1.1
Name: contactbox
Version: 0.1.8
Summary: 
